dmasyncwrapper/__init__.py
dmasyncwrapper/abstract.py
dmasyncwrapper/connection.py
dmasyncwrapper/consts.py
dmasyncwrapper/cursor.py
dmasyncwrapper/logger.py
dmasyncwrapper/pooling.py
dmasyncwrapper/utils.py
dmasyncwrapper-0.0.1.dev21.dist-info/licenses/LICENSE
dmasyncwrapper-0.0.1.dev21.dist-info/METADATA
dmasyncwrapper-0.0.1.dev21.dist-info/WHEEL
dmasyncwrapper-0.0.1.dev21.dist-info/top_level.txt
dmasyncwrapper-0.0.1.dev21.dist-info/RECORD
