Metadata-Version: 2.4
Name: dmasyncwrapper
Version: 0.0.1.dev21
Summary: DaMeng Async Wrapper
Author-email: "M@gicAgCl(DEAD)" <wyqsmith@aegeanstudio.com>
Requires-Python: >=3.12
License-File: LICENSE
Dynamic: license-file
